LICENSE
MANIFEST.in
README.md
setup.py
django_notification/__init__.py
django_notification/settings.py
django_notification/urls.py
django_notification/wsgi.py
django_webline_notifications.egg-info/PKG-INFO
django_webline_notifications.egg-info/SOURCES.txt
django_webline_notifications.egg-info/dependency_links.txt
django_webline_notifications.egg-info/requires.txt
django_webline_notifications.egg-info/top_level.txt
webline_notifications/__init__.py
webline_notifications/admin.py
webline_notifications/models.py
webline_notifications/tests.py
webline_notifications/urls.py
webline_notifications/views.py
webline_notifications/migrations/0001_initial.py
webline_notifications/migrations/__init__.py
webline_notifications/static/webline_notifications/ns-style.css
webline_notifications/static/webline_notifications/font-awesome/css/font-awesome.css
webline_notifications/static/webline_notifications/font-awesome/css/font-awesome.min.css
webline_notifications/static/webline_notifications/font-awesome/fonts/FontAwesome.otf
webline_notifications/static/webline_notifications/font-awesome/fonts/fontawesome-webfont.eot
webline_notifications/static/webline_notifications/font-awesome/fonts/fontawesome-webfont.svg
webline_notifications/static/webline_notifications/font-awesome/fonts/fontawesome-webfont.ttf
webline_notifications/static/webline_notifications/font-awesome/fonts/fontawesome-webfont.woff
webline_notifications/static/webline_notifications/font-awesome/fonts/fontawesome-webfont.woff2
webline_notifications/static/webline_notifications/jquery/jquery-1.11.3.min.js
webline_notifications/templates/admin/base_site.html
webline_notifications/templates/notification/nav_link.html
webline_notifications/templatetags/Notifications_tag.py
webline_notifications/templatetags/Notifications_tag.pyc
webline_notifications/templatetags/__init__.py
webline_notifications/templatetags/__init__.pyc