Metadata-Version: 1.1
Name: django-webline-notifications
Version: 1.0.1
Summary: A simple Django app which allow you notify everything to user or users
Home-page: https://github.com/alireza-molaee/django-webline-notifications
Author: alireza molaee
Author-email: alirezamolaii@gmail.com
License: GNU General Public License (GPL)
Platform: UNKNOWN
Classifier: Environment :: Web Environment
Classifier: Framework :: Django
Classifier: Intended Audience :: Developers
Classifier: Intended Audience :: System Administrators
Classifier: License :: OSI Approved :: GNU General Public License (GPL)
Classifier: Operating System :: OS Independent
Classifier: Programming Language :: Python
Classifier: Programming Language :: Python :: 2.7
Classifier: Programming Language :: Python :: 3.4
Classifier: Topic :: Internet :: WWW/HTTP
Classifier: Topic :: Software Development :: Libraries :: Python Modules
